equilib/__init__.py
equilib-0.0.1.dist-info/METADATA
equilib-0.0.1.dist-info/RECORD
equilib-0.0.1.dist-info/WHEEL
equilib-0.0.1.dist-info/top_level.txt
